MANIFEST.in
README.rst
setup.py
doc/changes.rst
doc/contributors.rst
src/mllib/__init__.py
src/mllib/config.py
src/mllib/documents.py
src/mllib/eval.py
src/mllib/mlexceptions.py
src/mllib/restclient.py
src/mllib/utils.py
src/mllib.egg-info/PKG-INFO
src/mllib.egg-info/SOURCES.txt
src/mllib.egg-info/dependency_links.txt
src/mllib.egg-info/not-zip-safe
src/mllib.egg-info/requires.txt
src/mllib.egg-info/top_level.txt