Metadata-Version: 1.1
Name: mllib
Version: 1.0.0a2
Summary: A REST client for MarkLogic 8
Home-page: http://pypi.python.org/pypi/mllib
Author: Gilles Lenfant
Author-email: gilles.lenfant@alterway.fr
License: MIT
Platform: UNKNOWN
Classifier: Development Status :: 2 - Pre-Alpha
Classifier: Programming Language :: Python
Classifier: Programming Language :: Python :: 2.7
Classifier: Topic :: Software Development :: Documentation
Classifier: Topic :: Database :: Front-Ends
Classifier: License :: OSI Approved :: MIT License
Classifier: Operating System :: OS Independent
